setup.py
src/lck/__init__.py
src/lck.i18n.egg-info/PKG-INFO
src/lck.i18n.egg-info/SOURCES.txt
src/lck.i18n.egg-info/dependency_links.txt
src/lck.i18n.egg-info/namespace_packages.txt
src/lck.i18n.egg-info/requires.txt
src/lck.i18n.egg-info/top_level.txt
src/lck.i18n.egg-info/zip-safe
src/lck/i18n/__init__.py
src/lck/i18n/potool.py
src/lck/i18n/urls.py
src/lck/i18n/translit/__init__.py
src/lck/i18n/translit/custom.py
src/lck/i18n/translit/uconv.py
test/test_transliteration.py