Metadata-Version: 1.0
Name: lck.i18n
Version: 0.3.0
Summary: Various common i18n-related routines.
Home-page: UNKNOWN
Author: Lukasz Langa, Krzysztof Borowczyk
Author-email: lukasz@langa.pl, krzysztof@bordev.pl
License: GPL v3
Platform: any
Classifier: Development Status :: 4 - Beta
Classifier: Intended Audience :: Developers
Classifier: License :: OSI Approved :: MIT License
Classifier: Natural Language :: English
Classifier: Programming Language :: Python
Classifier: Programming Language :: Python :: 2.7
Classifier: Topic :: Software Development :: Libraries :: Python Modules
